Abhi/Logging.py
Abhi/Misc.py
Abhi/__init__.py
Abhi/__main__.py
Abhi/Core/Bot.py
Abhi/Core/Userbot.py
Abhi/Core/__init__.py
Abhi/Plugins/__init__.py
Abhi/Plugins/Pytgcalls/Pytgcalls.py
Abhi/Plugins/Pytgcalls/__init__.py
Abhi/Plugins/Sounds/Others.py
Abhi/Plugins/Sounds/Play.py
Abhi/Plugins/Sounds/Playlist.py
Abhi/Plugins/Sounds/Seek.py
Abhi/Plugins/Sounds/Skip.py
Abhi/Plugins/Sounds/Vplay.py
Abhi/Plugins/Sounds/__init__.py
Abhi/Plugins/Start/Alive.py
Abhi/Plugins/Start/Start.py
Abhi/Plugins/Start/__init__.py
Abhi/Plugins/Sudocmd/Speedtest.py
Abhi/Plugins/Sudocmd/Sudo.py
Abhi/Plugins/Sudocmd/__init__.py
Abhi/Test/Test.py
Abhi/Test/__init__.py
Abhi/Utils/Delete.py
Abhi/Utils/Formaters.py
Abhi/Utils/Loop.py
Abhi/Utils/Queue.py
Abhi/Utils/YtDetails.py
Abhi/Utils/__init__.py
Config/Config.py
Config/__init__.py
Music/Logging.py
Music/Misc.py
Music/__init__.py
Music/__main__.py
Music/Core/Bot.py
Music/Core/UserBot.py
Music/Core/__init__.py
abhimusicplug-1.1.0.dist-info/licenses/LICENSE
abhimusicplug-1.1.0.dist-info/METADATA
abhimusicplug-1.1.0.dist-info/WHEEL
abhimusicplug-1.1.0.dist-info/top_level.txt
abhimusicplug-1.1.0.dist-info/RECORD
